{
	"info": {
		"_postman_id": "243333b9-6817-44c3-8436-758aa5c47658",
		"name": "smolurl",
		"schema": "https://schema.getpostman.com/json/collection/v2.1.0/collection.json",
		"_exporter_id": "29220201"
	},
	"item": [
		{
			"name": "CREATE",
			"request": {
				"method": "POST",
				"header": [],
				"body": {
					"mode": "raw",
					"raw": "{\r\n    \"url\": \"https://www.google.co.uk/\"\r\n}",
					"options": {
						"raw": {
							"language": "json"
						}
					}
				},
				"url": {
					"raw": "{{base_url}}/create",
					"host": [
						"{{base_url}}"
					],
					"path": [
						"create"
					]
				}
			},
			"response": []
		},
		{
			"name": "RESOLVE",
			"request": {
				"method": "GET",
				"header": [],
				"url": {
					"raw": "{{base_url}}/7659edef-ce2a-58a2-a7da-2875fc9134cc",
					"host": [
						"{{base_url}}"
					],
					"path": [
						"7659edef-ce2a-58a2-a7da-2875fc9134cc"
					]
				}
			},
			"response": []
		}
	],
	"event": [
		{
			"listen": "prerequest",
			"script": {
				"type": "text/javascript",
				"packages": {},
				"exec": [
					""
				]
			}
		},
		{
			"listen": "test",
			"script": {
				"type": "text/javascript",
				"packages": {},
				"exec": [
					""
				]
			}
		}
	],
	"variable": [
		{
			"key": "base_url",
			"value": "localhost:8080",
			"type": "string"
		}
	]
}